{
    "train": [
        {
            "loss": 1.8800708973112932,
            "Simple EM": 2.4583615020588776e-05,
            "QuAC F1": 0.05995031107753366,
            "epoch": 0
        },
        {
            "loss": 1.6645021169573293,
            "Simple EM": 8.604265257206072e-05,
            "QuAC F1": 0.12049526064407481,
            "epoch": 1
        },
        {
            "loss": 1.5161004061243564,
            "Simple EM": 9.83344600823551e-05,
            "QuAC F1": 0.14882811457819778,
            "epoch": 2
        }
    ],
    "valid": [
        {
            "loss": 8.55458063420505,
            "Simple EM": 0.0,
            "QuAC F1": 0.21657098826642807,
            "epoch": 0
        },
        {
            "loss": 8.473477985342138,
            "Simple EM": 0.0,
            "QuAC F1": 0.3493997279880108,
            "epoch": 1
        },
        {
            "loss": 8.462891687995427,
            "Simple EM": 0.0,
            "QuAC F1": 0.23719631575917136,
            "epoch": 2
        }
    ]
}