{
    "train": [
        {
            "loss": 1.3768440965996893,
            "Simple EM": 0.002837941521765255,
            "QuAC F1": 0.28599135108563556,
            "epoch": 0
        },
        {
            "loss": 0.92007831448248,
            "Simple EM": 0.006729711491352136,
            "QuAC F1": 0.46282059684014526,
            "epoch": 1
        },
        {
            "loss": 0.732584893304839,
            "Simple EM": 0.0078112722667480145,
            "QuAC F1": 0.5433046492185,
            "epoch": 2
        }
    ],
    "valid": [
        {
            "loss": 4.787354764659219,
            "Simple EM": 0.00576224477013654,
            "QuAC F1": 0.5436528429253386,
            "epoch": 0
        },
        {
            "loss": 4.54089616214808,
            "Simple EM": 0.007140172867343104,
            "QuAC F1": 0.5530962609497034,
            "epoch": 1
        },
        {
            "loss": 3.802892514415373,
            "Simple EM": 0.00864336715520481,
            "QuAC F1": 0.6164944359256068,
            "epoch": 2
        }
    ]
}