{
    "train": [
        {
            "loss": 1.3533203693893958,
            "Simple EM": 0.0027362563206596597,
            "QuAC F1": 0.29114843993988426,
            "epoch": 0
        },
        {
            "loss": 0.9118429939892846,
            "Simple EM": 0.006683490945395047,
            "QuAC F1": 0.46235457028967064,
            "epoch": 1
        },
        {
            "loss": 0.7320571030712363,
            "Simple EM": 0.007626390082919659,
            "QuAC F1": 0.5385754915566535,
            "epoch": 2
        }
    ],
    "valid": [
        {
            "loss": 4.721131993407282,
            "Simple EM": 0.005511712388826256,
            "QuAC F1": 0.5190758094368191,
            "epoch": 0
        },
        {
            "loss": 4.327312673042661,
            "Simple EM": 0.006764374295377677,
            "QuAC F1": 0.573033510434308,
            "epoch": 1
        },
        {
            "loss": 3.698992300510336,
            "Simple EM": 0.008142302392584242,
            "QuAC F1": 0.6129728854084183,
            "epoch": 2
        }
    ]
}